<?xml version="1.0" ?>
<GAMES>
    <GAME>
        <GAME_ID>1</GAME_ID>
        <PLAYER_1>Jarda</PLAYER_1>
        <PLAYER_2>Vitek</PLAYER_2>
        <DATE>1208645281</DATE>
        <ON_STEP>Vitek</ON_STEP>
        <FINISHED>0</FINISHED>
        <GAMESTEPS last_step_id="47">
            <STEP step_id="0">
                <DATA>11</DATA>
                <DATA>15</DATA>
            </STEP>
            <STEP step_id="1">
                <DATA>9</DATA>
                <DATA>13</DATA>
            </STEP>
            <STEP step_id="2">
                <DATA>15</DATA>
                <DATA>22</DATA>
            </STEP>
            <STEP step_id="3">
                <DATA>6</DATA>
                <DATA>13</DATA>
            </STEP>
            <STEP step_id="4">
                <DATA>10</DATA>
                <DATA>15</DATA>
            </STEP>
            <STEP step_id="5">
                <DATA>13</DATA>
                <DATA>20</DATA>
            </STEP>
            <STEP step_id="6">
                <DATA>7</DATA>
                <DATA>10</DATA>
            </STEP>
            <STEP step_id="7">
                <DATA>20</DATA>
                <DATA>24</DATA>
            </STEP>
            <STEP step_id="8">
                <DATA>2</DATA>
                <DATA>11</DATA>
            </STEP>
            <STEP step_id="9">
                <DATA>10</DATA>
                <DATA>14</DATA>
            </STEP>
            <STEP step_id="10">
                <DATA>10</DATA>
                <DATA>14</DATA>
            </STEP>
            <STEP step_id="11">
                <DATA>14</DATA>
                <DATA>21</DATA>
            </STEP>
            <STEP step_id="12">
                <DATA>6</DATA>
                <DATA>15</DATA>
            </STEP>
            <STEP step_id="13">
                <DATA>8</DATA>
                <DATA>13</DATA>
            </STEP>
            <STEP step_id="14">
                <DATA>15</DATA>
                <DATA>22</DATA>
            </STEP>
            <STEP step_id="15">
                <DATA>5</DATA>
                <DATA>14</DATA>
            </STEP>
            <STEP step_id="16">
                <DATA>9</DATA>
                <DATA>14</DATA>
            </STEP>
            <STEP step_id="17">
                <DATA>14</DATA>
                <DATA>21</DATA>
            </STEP>
            <STEP step_id="18">
                <DATA>1</DATA>
                <DATA>6</DATA>
            </STEP>
            <STEP step_id="19">
                <DATA>21</DATA>
                <DATA>30</DATA>
            </STEP>
            <STEP step_id="20">
                <DATA>11</DATA>
                <DATA>15</DATA>
            </STEP>
            <STEP step_id="21">
                <DATA>30</DATA>
                <DATA>12</DATA>
            </STEP>
            <STEP step_id="22">
                <DATA>5</DATA>
                <DATA>9</DATA>
            </STEP>
            <STEP step_id="23">
                <DATA>12</DATA>
                <DATA>8</DATA>
            </STEP>
            <STEP step_id="24">
                <DATA>0</DATA>
                <DATA>5</DATA>
            </STEP>
            <STEP step_id="25">
                <DATA>7</DATA>
                <DATA>10</DATA>
            </STEP>
            <STEP step_id="26">
                <DATA>8</DATA>
                <DATA>12</DATA>
            </STEP>
            <STEP step_id="27">
                <DATA>1</DATA>
                <DATA>6</DATA>
            </STEP>
            <STEP step_id="28">
                <DATA>3</DATA>
                <DATA>7</DATA>
            </STEP>
            <STEP step_id="29">
                <DATA>10</DATA>
                <DATA>15</DATA>
            </STEP>
            <STEP step_id="30">
                <DATA>12</DATA>
                <DATA>21</DATA>
                <DATA>21</DATA>
                <DATA>30</DATA>
            </STEP>
            <STEP step_id="31">
                <DATA>2</DATA>
                <DATA>6</DATA>
            </STEP>
            <STEP step_id="32">
                <DATA>30</DATA>
                <DATA>19</DATA>
            </STEP>
            <STEP step_id="33">
                <DATA>6</DATA>
                <DATA>9</DATA>
            </STEP>
            <STEP step_id="34">
                <DATA>19</DATA>
                <DATA>26</DATA>
            </STEP>
            <STEP step_id="35">
                <DATA>9</DATA>
                <DATA>14</DATA>
            </STEP>
            <STEP step_id="36">
                <DATA>26</DATA>
                <DATA>13</DATA>
            </STEP>
            <STEP step_id="37">
                <DATA>11</DATA>
                <DATA>15</DATA>
            </STEP>
            <STEP step_id="38">
                <DATA>13</DATA>
                <DATA>20</DATA>
            </STEP>
            <STEP step_id="39">
                <DATA>3</DATA>
                <DATA>7</DATA>
            </STEP>
            <STEP step_id="40">
                <DATA>20</DATA>
                <DATA>29</DATA>
            </STEP>
            <STEP step_id="41">
                <DATA>0</DATA>
                <DATA>5</DATA>
            </STEP>
            <STEP step_id="42">
                <DATA>9</DATA>
                <DATA>14</DATA>
            </STEP>
            <STEP step_id="43">
                <DATA>5</DATA>
                <DATA>9</DATA>
            </STEP>
            <STEP step_id="44">
                <DATA>29</DATA>
                <DATA>18</DATA>
            </STEP>
            <STEP step_id="45">
                <DATA>4</DATA>
                <DATA>8</DATA>
            </STEP>
            <STEP step_id="46">
                <DATA>18</DATA>
                <DATA>27</DATA>
            </STEP>
        </GAMESTEPS>
    </GAME>
    <GAME>
        <GAME_ID>2</GAME_ID>
        <PLAYER_1>Max</PLAYER_1>
        <PLAYER_2>Jarda</PLAYER_2>
        <DATE>1208645441</DATE>
        <ON_STEP>Max</ON_STEP>
        <FINISHED>0</FINISHED>
        <GAMESTEPS last_step_id="46">
            <STEP step_id="0">
                <DATA>11</DATA>
                <DATA>15</DATA>
            </STEP>
            <STEP step_id="1">
                <DATA>9</DATA>
                <DATA>13</DATA>
            </STEP>
            <STEP step_id="2">
                <DATA>15</DATA>
                <DATA>22</DATA>
            </STEP>
            <STEP step_id="3">
                <DATA>6</DATA>
                <DATA>13</DATA>
            </STEP>
            <STEP step_id="4">
                <DATA>9</DATA>
                <DATA>14</DATA>
            </STEP>
            <STEP step_id="5">
                <DATA>13</DATA>
                <DATA>22</DATA>
            </STEP>
            <STEP step_id="6">
                <DATA>5</DATA>
                <DATA>14</DATA>
            </STEP>
            <STEP step_id="7">
                <DATA>10</DATA>
                <DATA>14</DATA>
            </STEP>
            <STEP step_id="8">
                <DATA>14</DATA>
                <DATA>21</DATA>
            </STEP>
            <STEP step_id="9">
                <DATA>7</DATA>
                <DATA>14</DATA>
            </STEP>
            <STEP step_id="10">
                <DATA>8</DATA>
                <DATA>12</DATA>
            </STEP>
            <STEP step_id="11">
                <DATA>11</DATA>
                <DATA>15</DATA>
            </STEP>
            <STEP step_id="12">
                <DATA>12</DATA>
                <DATA>21</DATA>
            </STEP>
            <STEP step_id="13">
                <DATA>14</DATA>
                <DATA>17</DATA>
            </STEP>
            <STEP step_id="14">
                <DATA>10</DATA>
                <DATA>17</DATA>
            </STEP>
            <STEP step_id="15">
                <DATA>1</DATA>
                <DATA>6</DATA>
            </STEP>
            <STEP step_id="16">
                <DATA>21</DATA>
                <DATA>30</DATA>
            </STEP>
            <STEP step_id="17">
                <DATA>3</DATA>
                <DATA>7</DATA>
            </STEP>
            <STEP step_id="18">
                <DATA>6</DATA>
                <DATA>9</DATA>
            </STEP>
            <STEP step_id="19">
                <DATA>8</DATA>
                <DATA>12</DATA>
            </STEP>
            <STEP step_id="20">
                <DATA>30</DATA>
                <DATA>23</DATA>
            </STEP>
            <STEP step_id="21">
                <DATA>4</DATA>
                <DATA>13</DATA>
            </STEP>
            <STEP step_id="22">
                <DATA>7</DATA>
                <DATA>11</DATA>
            </STEP>
            <STEP step_id="23">
                <DATA>2</DATA>
                <DATA>6</DATA>
            </STEP>
            <STEP step_id="24">
                <DATA>4</DATA>
                <DATA>8</DATA>
            </STEP>
            <STEP step_id="25">
                <DATA>6</DATA>
                <DATA>9</DATA>
            </STEP>
            <STEP step_id="26">
                <DATA>17</DATA>
                <DATA>26</DATA>
            </STEP>
            <STEP step_id="27">
                <DATA>0</DATA>
                <DATA>9</DATA>
            </STEP>
            <STEP step_id="28">
                <DATA>11</DATA>
                <DATA>15</DATA>
            </STEP>
            <STEP step_id="29">
                <DATA>13</DATA>
                <DATA>20</DATA>
            </STEP>
            <STEP step_id="30">
                <DATA>2</DATA>
                <DATA>7</DATA>
            </STEP>
            <STEP step_id="31">
                <DATA>20</DATA>
                <DATA>29</DATA>
            </STEP>
            <STEP step_id="32">
                <DATA>9</DATA>
                <DATA>13</DATA>
            </STEP>
            <STEP step_id="33">
                <DATA>29</DATA>
                <DATA>15</DATA>
            </STEP>
            <STEP step_id="34">
                <DATA>1</DATA>
                <DATA>6</DATA>
            </STEP>
            <STEP step_id="35">
                <DATA>15</DATA>
                <DATA>29</DATA>
            </STEP>
            <STEP step_id="36">
                <DATA>3</DATA>
                <DATA>7</DATA>
            </STEP>
            <STEP step_id="37">
                <DATA>29</DATA>
                <DATA>20</DATA>
            </STEP>
            <STEP step_id="38">
                <DATA>8</DATA>
                <DATA>13</DATA>
            </STEP>
            <STEP step_id="39">
                <DATA>9</DATA>
                <DATA>14</DATA>
            </STEP>
            <STEP step_id="40">
                <DATA>13</DATA>
                <DATA>22</DATA>
            </STEP>
            <STEP step_id="41">
                <DATA>20</DATA>
                <DATA>6</DATA>
            </STEP>
            <STEP step_id="42">
                <DATA>0</DATA>
                <DATA>4</DATA>
            </STEP>
            <STEP step_id="43">
                <DATA>6</DATA>
                <DATA>19</DATA>
            </STEP>
            <STEP step_id="44">
                <DATA>4</DATA>
                <DATA>8</DATA>
            </STEP>
            <STEP step_id="45">
                <DATA>19</DATA>
                <DATA>26</DATA>
            </STEP>
        </GAMESTEPS>
    </GAME>
    <GAME>
        <GAME_ID>3</GAME_ID>
        <PLAYER_1>Milos</PLAYER_1>
        <PLAYER_2>Jarda</PLAYER_2>
        <DATE>1208645519</DATE>
        <ON_STEP>Jarda</ON_STEP>
        <FINISHED>0</FINISHED>
        <GAMESTEPS last_step_id="19">
            <STEP step_id="0">
                <DATA>11</DATA>
                <DATA>15</DATA>
            </STEP>
            <STEP step_id="1">
                <DATA>10</DATA>
                <DATA>15</DATA>
            </STEP>
            <STEP step_id="2">
                <DATA>10</DATA>
                <DATA>14</DATA>
            </STEP>
            <STEP step_id="3">
                <DATA>9</DATA>
                <DATA>14</DATA>
            </STEP>
            <STEP step_id="4">
                <DATA>14</DATA>
                <DATA>21</DATA>
            </STEP>
            <STEP step_id="5">
                <DATA>7</DATA>
                <DATA>14</DATA>
            </STEP>
            <STEP step_id="6">
                <DATA>9</DATA>
                <DATA>14</DATA>
            </STEP>
            <STEP step_id="7">
                <DATA>14</DATA>
                <DATA>21</DATA>
            </STEP>
            <STEP step_id="8">
                <DATA>7</DATA>
                <DATA>14</DATA>
            </STEP>
            <STEP step_id="9">
                <DATA>6</DATA>
                <DATA>10</DATA>
            </STEP>
            <STEP step_id="10">
                <DATA>6</DATA>
                <DATA>9</DATA>
            </STEP>
            <STEP step_id="11">
                <DATA>10</DATA>
                <DATA>14</DATA>
            </STEP>
            <STEP step_id="12">
                <DATA>14</DATA>
                <DATA>21</DATA>
            </STEP>
            <STEP step_id="13">
                <DATA>15</DATA>
                <DATA>19</DATA>
            </STEP>
            <STEP step_id="14">
                <DATA>9</DATA>
                <DATA>13</DATA>
            </STEP>
            <STEP step_id="15">
                <DATA>11</DATA>
                <DATA>15</DATA>
            </STEP>
            <STEP step_id="16">
                <DATA>13</DATA>
                <DATA>20</DATA>
            </STEP>
            <STEP step_id="17">
                <DATA>1</DATA>
                <DATA>6</DATA>
            </STEP>
            <STEP step_id="18">
                <DATA>21</DATA>
                <DATA>30</DATA>
            </STEP>
        </GAMESTEPS>
    </GAME>
    <GAME>
        <GAME_ID>5</GAME_ID>
        <PLAYER_1>Milos</PLAYER_1>
        <PLAYER_2>Vitek</PLAYER_2>
        <DATE>1208645988</DATE>
        <ON_STEP>Milos</ON_STEP>
        <FINISHED>0</FINISHED>
        <GAMESTEPS last_step_id="56">
            <STEP step_id="0">
                <DATA>11</DATA>
                <DATA>15</DATA>
            </STEP>
            <STEP step_id="1">
                <DATA>10</DATA>
                <DATA>15</DATA>
            </STEP>
            <STEP step_id="2">
                <DATA>8</DATA>
                <DATA>12</DATA>
            </STEP>
            <STEP step_id="3">
                <DATA>6</DATA>
                <DATA>10</DATA>
            </STEP>
            <STEP step_id="4">
                <DATA>9</DATA>
                <DATA>13</DATA>
            </STEP>
            <STEP step_id="5">
                <DATA>15</DATA>
                <DATA>22</DATA>
            </STEP>
            <STEP step_id="6">
                <DATA>6</DATA>
                <DATA>13</DATA>
            </STEP>
            <STEP step_id="7">
                <DATA>10</DATA>
                <DATA>15</DATA>
            </STEP>
            <STEP step_id="8">
                <DATA>12</DATA>
                <DATA>21</DATA>
            </STEP>
            <STEP step_id="9">
                <DATA>7</DATA>
                <DATA>14</DATA>
                <DATA>14</DATA>
                <DATA>23</DATA>
            </STEP>
            <STEP step_id="10">
                <DATA>5</DATA>
                <DATA>12</DATA>
            </STEP>
            <STEP step_id="11">
                <DATA>2</DATA>
                <DATA>7</DATA>
            </STEP>
            <STEP step_id="12">
                <DATA>1</DATA>
                <DATA>5</DATA>
            </STEP>
            <STEP step_id="13">
                <DATA>8</DATA>
                <DATA>13</DATA>
            </STEP>
            <STEP step_id="14">
                <DATA>10</DATA>
                <DATA>14</DATA>
            </STEP>
            <STEP step_id="15">
                <DATA>13</DATA>
                <DATA>22</DATA>
            </STEP>
            <STEP step_id="16">
                <DATA>5</DATA>
                <DATA>14</DATA>
            </STEP>
            <STEP step_id="17">
                <DATA>4</DATA>
                <DATA>8</DATA>
            </STEP>
            <STEP step_id="18">
                <DATA>7</DATA>
                <DATA>10</DATA>
            </STEP>
            <STEP step_id="19">
                <DATA>9</DATA>
                <DATA>14</DATA>
            </STEP>
            <STEP step_id="20">
                <DATA>14</DATA>
                <DATA>21</DATA>
            </STEP>
            <STEP step_id="21">
                <DATA>7</DATA>
                <DATA>14</DATA>
            </STEP>
            <STEP step_id="22">
                <DATA>3</DATA>
                <DATA>7</DATA>
            </STEP>
            <STEP step_id="23">
                <DATA>14</DATA>
                <DATA>17</DATA>
            </STEP>
            <STEP step_id="24">
                <DATA>10</DATA>
                <DATA>17</DATA>
            </STEP>
            <STEP step_id="25">
                <DATA>3</DATA>
                <DATA>7</DATA>
            </STEP>
            <STEP step_id="26">
                <DATA>12</DATA>
                <DATA>16</DATA>
            </STEP>
            <STEP step_id="27">
                <DATA>11</DATA>
                <DATA>18</DATA>
            </STEP>
            <STEP step_id="28">
                <DATA>0</DATA>
                <DATA>5</DATA>
            </STEP>
            <STEP step_id="29">
                <DATA>1</DATA>
                <DATA>6</DATA>
            </STEP>
            <STEP step_id="30">
                <DATA>4</DATA>
                <DATA>8</DATA>
            </STEP>
            <STEP step_id="31">
                <DATA>18</DATA>
                <DATA>27</DATA>
            </STEP>
            <STEP step_id="32">
                <DATA>17</DATA>
                <DATA>22</DATA>
            </STEP>
            <STEP step_id="33">
                <DATA>6</DATA>
                <DATA>13</DATA>
                <DATA>13</DATA>
                <DATA>20</DATA>
            </STEP>
            <STEP step_id="34">
                <DATA>2</DATA>
                <DATA>6</DATA>
            </STEP>
            <STEP step_id="35">
                <DATA>20</DATA>
                <DATA>29</DATA>
            </STEP>
            <STEP step_id="36">
                <DATA>6</DATA>
                <DATA>9</DATA>
            </STEP>
            <STEP step_id="37">
                <DATA>29</DATA>
                <DATA>18</DATA>
            </STEP>
            <STEP step_id="38">
                <DATA>5</DATA>
                <DATA>8</DATA>
            </STEP>
            <STEP step_id="39">
                <DATA>7</DATA>
                <DATA>10</DATA>
            </STEP>
            <STEP step_id="40">
                <DATA>8</DATA>
                <DATA>17</DATA>
                <DATA>17</DATA>
                <DATA>24</DATA>
            </STEP>
            <STEP step_id="41">
                <DATA>5</DATA>
                <DATA>9</DATA>
            </STEP>
            <STEP step_id="42">
                <DATA>24</DATA>
                <DATA>29</DATA>
            </STEP>
            <STEP step_id="43">
                <DATA>8</DATA>
                <DATA>13</DATA>
            </STEP>
            <STEP step_id="44">
                <DATA>29</DATA>
                <DATA>25</DATA>
            </STEP>
            <STEP step_id="45">
                <DATA>0</DATA>
                <DATA>5</DATA>
            </STEP>
            <STEP step_id="46">
                <DATA>25</DATA>
                <DATA>30</DATA>
            </STEP>
            <STEP step_id="47">
                <DATA>5</DATA>
                <DATA>8</DATA>
            </STEP>
            <STEP step_id="48">
                <DATA>30</DATA>
                <DATA>19</DATA>
            </STEP>
            <STEP step_id="49">
                <DATA>13</DATA>
                <DATA>16</DATA>
            </STEP>
            <STEP step_id="50">
                <DATA>19</DATA>
                <DATA>10</DATA>
            </STEP>
            <STEP step_id="51">
                <DATA>9</DATA>
                <DATA>14</DATA>
            </STEP>
            <STEP step_id="52">
                <DATA>10</DATA>
                <DATA>21</DATA>
            </STEP>
            <STEP step_id="53">
                <DATA>27</DATA>
                <DATA>31</DATA>
            </STEP>
            <STEP step_id="54">
                <DATA>21</DATA>
                <DATA>14</DATA>
            </STEP>
            <STEP step_id="55">
                <DATA>31</DATA>
                <DATA>13</DATA>
            </STEP>
        </GAMESTEPS>
    </GAME>
    <GAME>
        <GAME_ID>6</GAME_ID>
        <PLAYER_1>Max</PLAYER_1>
        <PLAYER_2>Milos</PLAYER_2>
        <DATE>1208646254</DATE>
        <ON_STEP>Max</ON_STEP>
        <FINISHED>0</FINISHED>
        <GAMESTEPS last_step_id="28">
            <STEP step_id="0">
                <DATA>11</DATA>
                <DATA>15</DATA>
            </STEP>
            <STEP step_id="1">
                <DATA>8</DATA>
                <DATA>13</DATA>
            </STEP>
            <STEP step_id="2">
                <DATA>7</DATA>
                <DATA>11</DATA>
            </STEP>
            <STEP step_id="3">
                <DATA>5</DATA>
                <DATA>8</DATA>
            </STEP>
            <STEP step_id="4">
                <DATA>2</DATA>
                <DATA>7</DATA>
            </STEP>
            <STEP step_id="5">
                <DATA>8</DATA>
                <DATA>12</DATA>
            </STEP>
            <STEP step_id="6">
                <DATA>10</DATA>
                <DATA>14</DATA>
            </STEP>
            <STEP step_id="7">
                <DATA>12</DATA>
                <DATA>21</DATA>
            </STEP>
            <STEP step_id="8">
                <DATA>6</DATA>
                <DATA>15</DATA>
            </STEP>
            <STEP step_id="9">
                <DATA>4</DATA>
                <DATA>8</DATA>
            </STEP>
            <STEP step_id="10">
                <DATA>15</DATA>
                <DATA>19</DATA>
            </STEP>
            <STEP step_id="11">
                <DATA>0</DATA>
                <DATA>5</DATA>
            </STEP>
            <STEP step_id="12">
                <DATA>8</DATA>
                <DATA>12</DATA>
            </STEP>
            <STEP step_id="13">
                <DATA>11</DATA>
                <DATA>15</DATA>
            </STEP>
            <STEP step_id="14">
                <DATA>4</DATA>
                <DATA>8</DATA>
            </STEP>
            <STEP step_id="15">
                <DATA>9</DATA>
                <DATA>14</DATA>
            </STEP>
            <STEP step_id="16">
                <DATA>9</DATA>
                <DATA>13</DATA>
            </STEP>
            <STEP step_id="17">
                <DATA>13</DATA>
                <DATA>22</DATA>
            </STEP>
            <STEP step_id="18">
                <DATA>5</DATA>
                <DATA>14</DATA>
            </STEP>
            <STEP step_id="19">
                <DATA>14</DATA>
                <DATA>21</DATA>
            </STEP>
            <STEP step_id="20">
                <DATA>7</DATA>
                <DATA>14</DATA>
            </STEP>
            <STEP step_id="21">
                <DATA>15</DATA>
                <DATA>22</DATA>
            </STEP>
            <STEP step_id="22">
                <DATA>0</DATA>
                <DATA>5</DATA>
            </STEP>
            <STEP step_id="23">
                <DATA>22</DATA>
                <DATA>31</DATA>
            </STEP>
            <STEP step_id="24">
                <DATA>8</DATA>
                <DATA>13</DATA>
            </STEP>
            <STEP step_id="25">
                <DATA>31</DATA>
                <DATA>13</DATA>
            </STEP>
            <STEP step_id="26">
                <DATA>11</DATA>
                <DATA>15</DATA>
            </STEP>
            <STEP step_id="27">
                <DATA>13</DATA>
                <DATA>20</DATA>
            </STEP>
        </GAMESTEPS>
    </GAME>
    <GAME>
        <GAME_ID>7</GAME_ID>
        <PLAYER_1>Vitek</PLAYER_1>
        <PLAYER_2>Jarda</PLAYER_2>
        <DATE>1208646765</DATE>
        <ON_STEP>Vitek</ON_STEP>
        <FINISHED>0</FINISHED>
        <GAMESTEPS last_step_id="26">
            <STEP step_id="0">
                <DATA>11</DATA>
                <DATA>15</DATA>
            </STEP>
            <STEP step_id="1">
                <DATA>11</DATA>
                <DATA>15</DATA>
            </STEP>
            <STEP step_id="2">
                <DATA>9</DATA>
                <DATA>13</DATA>
            </STEP>
            <STEP step_id="3">
                <DATA>15</DATA>
                <DATA>22</DATA>
            </STEP>
            <STEP step_id="4">
                <DATA>5</DATA>
                <DATA>14</DATA>
            </STEP>
            <STEP step_id="5">
                <DATA>9</DATA>
                <DATA>13</DATA>
            </STEP>
            <STEP step_id="6">
                <DATA>15</DATA>
                <DATA>22</DATA>
            </STEP>
            <STEP step_id="7">
                <DATA>6</DATA>
                <DATA>13</DATA>
                <DATA>13</DATA>
                <DATA>22</DATA>
            </STEP>
            <STEP step_id="8">
                <DATA>6</DATA>
                <DATA>13</DATA>
            </STEP>
            <STEP step_id="9">
                <DATA>10</DATA>
                <DATA>14</DATA>
            </STEP>
            <STEP step_id="10">
                <DATA>13</DATA>
                <DATA>22</DATA>
            </STEP>
            <STEP step_id="11">
                <DATA>5</DATA>
                <DATA>14</DATA>
            </STEP>
            <STEP step_id="12">
                <DATA>8</DATA>
                <DATA>13</DATA>
            </STEP>
            <STEP step_id="13">
                <DATA>14</DATA>
                <DATA>23</DATA>
            </STEP>
            <STEP step_id="14">
                <DATA>4</DATA>
                <DATA>13</DATA>
            </STEP>
            <STEP step_id="15">
                <DATA>7</DATA>
                <DATA>11</DATA>
            </STEP>
            <STEP step_id="16">
                <DATA>13</DATA>
                <DATA>16</DATA>
            </STEP>
            <STEP step_id="17">
                <DATA>11</DATA>
                <DATA>18</DATA>
            </STEP>
            <STEP step_id="18">
                <DATA>0</DATA>
                <DATA>5</DATA>
            </STEP>
            <STEP step_id="19">
                <DATA>3</DATA>
                <DATA>7</DATA>
            </STEP>
            <STEP step_id="20">
                <DATA>5</DATA>
                <DATA>8</DATA>
            </STEP>
            <STEP step_id="21">
                <DATA>18</DATA>
                <DATA>27</DATA>
            </STEP>
            <STEP step_id="22">
                <DATA>1</DATA>
                <DATA>5</DATA>
            </STEP>
            <STEP step_id="23">
                <DATA>27</DATA>
                <DATA>31</DATA>
            </STEP>
            <STEP step_id="24">
                <DATA>5</DATA>
                <DATA>9</DATA>
            </STEP>
            <STEP step_id="25">
                <DATA>31</DATA>
                <DATA>17</DATA>
            </STEP>
        </GAMESTEPS>
    </GAME>
    <GAME>
        <GAME_ID>8</GAME_ID>
        <PLAYER_1>Jarda</PLAYER_1>
        <PLAYER_2>Max</PLAYER_2>
        <DATE>1208646899</DATE>
        <ON_STEP>Max</ON_STEP>
        <FINISHED>0</FINISHED>
        <GAMESTEPS last_step_id="23">
            <STEP step_id="0">
                <DATA>11</DATA>
                <DATA>15</DATA>
            </STEP>
            <STEP step_id="1">
                <DATA>8</DATA>
                <DATA>13</DATA>
            </STEP>
            <STEP step_id="2">
                <DATA>7</DATA>
                <DATA>11</DATA>
            </STEP>
            <STEP step_id="3">
                <DATA>4</DATA>
                <DATA>8</DATA>
            </STEP>
            <STEP step_id="4">
                <DATA>15</DATA>
                <DATA>19</DATA>
            </STEP>
            <STEP step_id="5">
                <DATA>13</DATA>
                <DATA>16</DATA>
            </STEP>
            <STEP step_id="6">
                <DATA>11</DATA>
                <DATA>18</DATA>
                <DATA>18</DATA>
                <DATA>27</DATA>
            </STEP>
            <STEP step_id="7">
                <DATA>11</DATA>
                <DATA>15</DATA>
            </STEP>
            <STEP step_id="8">
                <DATA>8</DATA>
                <DATA>12</DATA>
            </STEP>
            <STEP step_id="9">
                <DATA>7</DATA>
                <DATA>11</DATA>
            </STEP>
            <STEP step_id="10">
                <DATA>4</DATA>
                <DATA>8</DATA>
            </STEP>
            <STEP step_id="11">
                <DATA>9</DATA>
                <DATA>14</DATA>
            </STEP>
            <STEP step_id="12">
                <DATA>9</DATA>
                <DATA>13</DATA>
            </STEP>
            <STEP step_id="13">
                <DATA>15</DATA>
                <DATA>22</DATA>
            </STEP>
            <STEP step_id="14">
                <DATA>6</DATA>
                <DATA>13</DATA>
                <DATA>13</DATA>
                <DATA>22</DATA>
            </STEP>
            <STEP step_id="15">
                <DATA>6</DATA>
                <DATA>13</DATA>
            </STEP>
            <STEP step_id="16">
                <DATA>2</DATA>
                <DATA>7</DATA>
            </STEP>
            <STEP step_id="17">
                <DATA>10</DATA>
                <DATA>14</DATA>
            </STEP>
            <STEP step_id="18">
                <DATA>7</DATA>
                <DATA>11</DATA>
            </STEP>
            <STEP step_id="19">
                <DATA>3</DATA>
                <DATA>7</DATA>
            </STEP>
            <STEP step_id="20">
                <DATA>12</DATA>
                <DATA>16</DATA>
            </STEP>
            <STEP step_id="21">
                <DATA>11</DATA>
                <DATA>18</DATA>
                <DATA>18</DATA>
                <DATA>27</DATA>
            </STEP>
            <STEP step_id="22">
                <DATA>5</DATA>
                <DATA>8</DATA>
            </STEP>
        </GAMESTEPS>
    </GAME>
    <GAME>
        <GAME_ID>9</GAME_ID>
        <PLAYER_1>Vitek</PLAYER_1>
        <PLAYER_2>Milos</PLAYER_2>
        <DATE>1208647038</DATE>
        <ON_STEP>Milos</ON_STEP>
        <FINISHED>0</FINISHED>
        <GAMESTEPS last_step_id="17">
            <STEP step_id="0">
                <DATA>11</DATA>
                <DATA>15</DATA>
            </STEP>
            <STEP step_id="1">
                <DATA>8</DATA>
                <DATA>12</DATA>
            </STEP>
            <STEP step_id="2">
                <DATA>7</DATA>
                <DATA>11</DATA>
            </STEP>
            <STEP step_id="3">
                <DATA>9</DATA>
                <DATA>13</DATA>
            </STEP>
            <STEP step_id="4">
                <DATA>15</DATA>
                <DATA>22</DATA>
            </STEP>
            <STEP step_id="5">
                <DATA>5</DATA>
                <DATA>14</DATA>
            </STEP>
            <STEP step_id="6">
                <DATA>2</DATA>
                <DATA>7</DATA>
            </STEP>
            <STEP step_id="7">
                <DATA>6</DATA>
                <DATA>9</DATA>
            </STEP>
            <STEP step_id="8">
                <DATA>8</DATA>
                <DATA>12</DATA>
            </STEP>
            <STEP step_id="9">
                <DATA>9</DATA>
                <DATA>13</DATA>
            </STEP>
            <STEP step_id="10">
                <DATA>5</DATA>
                <DATA>8</DATA>
            </STEP>
            <STEP step_id="11">
                <DATA>2</DATA>
                <DATA>6</DATA>
            </STEP>
            <STEP step_id="12">
                <DATA>10</DATA>
                <DATA>15</DATA>
            </STEP>
            <STEP step_id="13">
                <DATA>12</DATA>
                <DATA>21</DATA>
            </STEP>
            <STEP step_id="14">
                <DATA>6</DATA>
                <DATA>15</DATA>
                <DATA>15</DATA>
                <DATA>22</DATA>
                <DATA>22</DATA>
                <DATA>29</DATA>
            </STEP>
            <STEP step_id="15">
                <DATA>1</DATA>
                <DATA>6</DATA>
            </STEP>
            <STEP step_id="16">
                <DATA>29</DATA>
                <DATA>22</DATA>
                <DATA>22</DATA>
                <DATA>13</DATA>
            </STEP>
        </GAMESTEPS>
    </GAME>
    <GAME>
        <GAME_ID>10</GAME_ID>
        <PLAYER_1>Jarda</PLAYER_1>
        <PLAYER_2>Milos</PLAYER_2>
        <DATE>1208647287</DATE>
        <ON_STEP>Jarda</ON_STEP>
        <FINISHED>0</FINISHED>
        <GAMESTEPS last_step_id="40">
            <STEP step_id="0">
                <DATA>11</DATA>
                <DATA>15</DATA>
            </STEP>
            <STEP step_id="1">
                <DATA>9</DATA>
                <DATA>13</DATA>
            </STEP>
            <STEP step_id="2">
                <DATA>15</DATA>
                <DATA>22</DATA>
            </STEP>
            <STEP step_id="3">
                <DATA>6</DATA>
                <DATA>13</DATA>
            </STEP>
            <STEP step_id="4">
                <DATA>7</DATA>
                <DATA>11</DATA>
            </STEP>
            <STEP step_id="5">
                <DATA>5</DATA>
                <DATA>9</DATA>
            </STEP>
            <STEP step_id="6">
                <DATA>2</DATA>
                <DATA>7</DATA>
            </STEP>
            <STEP step_id="7">
                <DATA>1</DATA>
                <DATA>6</DATA>
            </STEP>
            <STEP step_id="8">
                <DATA>9</DATA>
                <DATA>13</DATA>
            </STEP>
            <STEP step_id="9">
                <DATA>10</DATA>
                <DATA>15</DATA>
            </STEP>
            <STEP step_id="10">
                <DATA>8</DATA>
                <DATA>12</DATA>
            </STEP>
            <STEP step_id="11">
                <DATA>15</DATA>
                <DATA>22</DATA>
                <DATA>22</DATA>
                <DATA>29</DATA>
            </STEP>
            <STEP step_id="12">
                <DATA>10</DATA>
                <DATA>15</DATA>
            </STEP>
            <STEP step_id="13">
                <DATA>8</DATA>
                <DATA>12</DATA>
            </STEP>
            <STEP step_id="14">
                <DATA>7</DATA>
                <DATA>10</DATA>
            </STEP>
            <STEP step_id="15">
                <DATA>13</DATA>
                <DATA>17</DATA>
            </STEP>
            <STEP step_id="16">
                <DATA>10</DATA>
                <DATA>17</DATA>
                <DATA>17</DATA>
                <DATA>26</DATA>
            </STEP>
            <STEP step_id="17">
                <DATA>0</DATA>
                <DATA>9</DATA>
            </STEP>
            <STEP step_id="18">
                <DATA>4</DATA>
                <DATA>8</DATA>
            </STEP>
            <STEP step_id="19">
                <DATA>12</DATA>
                <DATA>21</DATA>
            </STEP>
            <STEP step_id="20">
                <DATA>11</DATA>
                <DATA>15</DATA>
            </STEP>
            <STEP step_id="21">
                <DATA>29</DATA>
                <DATA>25</DATA>
            </STEP>
            <STEP step_id="22">
                <DATA>15</DATA>
                <DATA>18</DATA>
            </STEP>
            <STEP step_id="23">
                <DATA>9</DATA>
                <DATA>16</DATA>
            </STEP>
            <STEP step_id="24">
                <DATA>5</DATA>
                <DATA>9</DATA>
            </STEP>
            <STEP step_id="25">
                <DATA>25</DATA>
                <DATA>18</DATA>
                <DATA>18</DATA>
                <DATA>27</DATA>
            </STEP>
            <STEP step_id="26">
                <DATA>0</DATA>
                <DATA>5</DATA>
            </STEP>
            <STEP step_id="27">
                <DATA>27</DATA>
                <DATA>23</DATA>
            </STEP>
            <STEP step_id="28">
                <DATA>5</DATA>
                <DATA>9</DATA>
            </STEP>
            <STEP step_id="29">
                <DATA>7</DATA>
                <DATA>10</DATA>
            </STEP>
            <STEP step_id="30">
                <DATA>3</DATA>
                <DATA>7</DATA>
            </STEP>
            <STEP step_id="31">
                <DATA>21</DATA>
                <DATA>28</DATA>
            </STEP>
            <STEP step_id="32">
                <DATA>1</DATA>
                <DATA>6</DATA>
            </STEP>
            <STEP step_id="33">
                <DATA>23</DATA>
                <DATA>26</DATA>
            </STEP>
            <STEP step_id="34">
                <DATA>9</DATA>
                <DATA>14</DATA>
            </STEP>
            <STEP step_id="35">
                <DATA>26</DATA>
                <DATA>13</DATA>
            </STEP>
            <STEP step_id="36">
                <DATA>6</DATA>
                <DATA>9</DATA>
            </STEP>
            <STEP step_id="37">
                <DATA>13</DATA>
                <DATA>26</DATA>
            </STEP>
            <STEP step_id="38">
                <DATA>12</DATA>
                <DATA>16</DATA>
            </STEP>
            <STEP step_id="39">
                <DATA>10</DATA>
                <DATA>19</DATA>
            </STEP>
        </GAMESTEPS>
    </GAME>
    <GAME>
        <GAME_ID>11</GAME_ID>
        <PLAYER_1>Max</PLAYER_1>
        <PLAYER_2>Milos</PLAYER_2>
        <DATE>1208647503</DATE>
        <ON_STEP>Max</ON_STEP>
        <FINISHED>0</FINISHED>
        <GAMESTEPS last_step_id="52">
            <STEP step_id="0">
                <DATA>11</DATA>
                <DATA>15</DATA>
            </STEP>
            <STEP step_id="1">
                <DATA>8</DATA>
                <DATA>12</DATA>
            </STEP>
            <STEP step_id="2">
                <DATA>7</DATA>
                <DATA>11</DATA>
            </STEP>
            <STEP step_id="3">
                <DATA>9</DATA>
                <DATA>13</DATA>
            </STEP>
            <STEP step_id="4">
                <DATA>15</DATA>
                <DATA>22</DATA>
            </STEP>
            <STEP step_id="5">
                <DATA>5</DATA>
                <DATA>14</DATA>
            </STEP>
            <STEP step_id="6">
                <DATA>2</DATA>
                <DATA>7</DATA>
            </STEP>
            <STEP step_id="7">
                <DATA>6</DATA>
                <DATA>9</DATA>
            </STEP>
            <STEP step_id="8">
                <DATA>8</DATA>
                <DATA>12</DATA>
            </STEP>
            <STEP step_id="9">
                <DATA>11</DATA>
                <DATA>15</DATA>
            </STEP>
            <STEP step_id="10">
                <DATA>5</DATA>
                <DATA>8</DATA>
            </STEP>
            <STEP step_id="11">
                <DATA>7</DATA>
                <DATA>11</DATA>
            </STEP>
            <STEP step_id="12">
                <DATA>0</DATA>
                <DATA>5</DATA>
            </STEP>
            <STEP step_id="13">
                <DATA>3</DATA>
                <DATA>7</DATA>
            </STEP>
            <STEP step_id="14">
                <DATA>11</DATA>
                <DATA>15</DATA>
            </STEP>
            <STEP step_id="15">
                <DATA>4</DATA>
                <DATA>8</DATA>
            </STEP>
            <STEP step_id="16">
                <DATA>7</DATA>
                <DATA>11</DATA>
            </STEP>
            <STEP step_id="17">
                <DATA>2</DATA>
                <DATA>6</DATA>
            </STEP>
            <STEP step_id="18">
                <DATA>3</DATA>
                <DATA>7</DATA>
            </STEP>
            <STEP step_id="19">
                <DATA>9</DATA>
                <DATA>13</DATA>
            </STEP>
            <STEP step_id="20">
                <DATA>15</DATA>
                <DATA>22</DATA>
                <DATA>22</DATA>
                <DATA>29</DATA>
            </STEP>
            <STEP step_id="21">
                <DATA>1</DATA>
                <DATA>6</DATA>
            </STEP>
            <STEP step_id="22">
                <DATA>29</DATA>
                <DATA>22</DATA>
                <DATA>22</DATA>
                <DATA>13</DATA>
            </STEP>
            <STEP step_id="23">
                <DATA>8</DATA>
                <DATA>13</DATA>
            </STEP>
            <STEP step_id="24">
                <DATA>9</DATA>
                <DATA>14</DATA>
            </STEP>
            <STEP step_id="25">
                <DATA>13</DATA>
                <DATA>22</DATA>
                <DATA>22</DATA>
                <DATA>31</DATA>
            </STEP>
            <STEP step_id="26">
                <DATA>1</DATA>
                <DATA>5</DATA>
            </STEP>
            <STEP step_id="27">
                <DATA>31</DATA>
                <DATA>22</DATA>
                <DATA>22</DATA>
                <DATA>29</DATA>
            </STEP>
            <STEP step_id="28">
                <DATA>10</DATA>
                <DATA>14</DATA>
            </STEP>
            <STEP step_id="29">
                <DATA>15</DATA>
                <DATA>22</DATA>
            </STEP>
            <STEP step_id="30">
                <DATA>8</DATA>
                <DATA>13</DATA>
            </STEP>
            <STEP step_id="31">
                <DATA>22</DATA>
                <DATA>26</DATA>
            </STEP>
            <STEP step_id="32">
                <DATA>12</DATA>
                <DATA>16</DATA>
            </STEP>
            <STEP step_id="33">
                <DATA>10</DATA>
                <DATA>19</DATA>
            </STEP>
            <STEP step_id="34">
                <DATA>4</DATA>
                <DATA>8</DATA>
            </STEP>
            <STEP step_id="35">
                <DATA>29</DATA>
                <DATA>15</DATA>
            </STEP>
            <STEP step_id="36">
                <DATA>14</DATA>
                <DATA>18</DATA>
            </STEP>
            <STEP step_id="37">
                <DATA>12</DATA>
                <DATA>16</DATA>
            </STEP>
            <STEP step_id="38">
                <DATA>18</DATA>
                <DATA>22</DATA>
            </STEP>
            <STEP step_id="39">
                <DATA>0</DATA>
                <DATA>5</DATA>
            </STEP>
            <STEP step_id="40">
                <DATA>11</DATA>
                <DATA>18</DATA>
            </STEP>
            <STEP step_id="41">
                <DATA>5</DATA>
                <DATA>14</DATA>
            </STEP>
            <STEP step_id="42">
                <DATA>8</DATA>
                <DATA>13</DATA>
            </STEP>
            <STEP step_id="43">
                <DATA>15</DATA>
                <DATA>22</DATA>
                <DATA>22</DATA>
                <DATA>8</DATA>
            </STEP>
            <STEP step_id="44">
                <DATA>7</DATA>
                <DATA>11</DATA>
            </STEP>
            <STEP step_id="45">
                <DATA>14</DATA>
                <DATA>17</DATA>
            </STEP>
            <STEP step_id="46">
                <DATA>11</DATA>
                <DATA>15</DATA>
            </STEP>
            <STEP step_id="47">
                <DATA>17</DATA>
                <DATA>21</DATA>
            </STEP>
            <STEP step_id="48">
                <DATA>15</DATA>
                <DATA>19</DATA>
            </STEP>
            <STEP step_id="49">
                <DATA>8</DATA>
                <DATA>13</DATA>
            </STEP>
            <STEP step_id="50">
                <DATA>19</DATA>
                <DATA>23</DATA>
            </STEP>
            <STEP step_id="51">
                <DATA>13</DATA>
                <DATA>4</DATA>
            </STEP>
        </GAMESTEPS>
    </GAME>
    <GAME>
        <GAME_ID>12</GAME_ID>
        <PLAYER_1>Vitek</PLAYER_1>
        <PLAYER_2>Max</PLAYER_2>
        <DATE>1208647792</DATE>
        <ON_STEP>Vitek</ON_STEP>
        <FINISHED>0</FINISHED>
        <GAMESTEPS last_step_id="70">
            <STEP step_id="0">
                <DATA>11</DATA>
                <DATA>15</DATA>
            </STEP>
            <STEP step_id="1">
                <DATA>9</DATA>
                <DATA>13</DATA>
            </STEP>
            <STEP step_id="2">
                <DATA>15</DATA>
                <DATA>22</DATA>
            </STEP>
            <STEP step_id="3">
                <DATA>6</DATA>
                <DATA>13</DATA>
            </STEP>
            <STEP step_id="4">
                <DATA>10</DATA>
                <DATA>15</DATA>
            </STEP>
            <STEP step_id="5">
                <DATA>13</DATA>
                <DATA>20</DATA>
            </STEP>
            <STEP step_id="6">
                <DATA>7</DATA>
                <DATA>10</DATA>
            </STEP>
            <STEP step_id="7">
                <DATA>20</DATA>
                <DATA>24</DATA>
            </STEP>
            <STEP step_id="8">
                <DATA>2</DATA>
                <DATA>11</DATA>
            </STEP>
            <STEP step_id="9">
                <DATA>8</DATA>
                <DATA>12</DATA>
            </STEP>
            <STEP step_id="10">
                <DATA>8</DATA>
                <DATA>12</DATA>
            </STEP>
            <STEP step_id="11">
                <DATA>11</DATA>
                <DATA>15</DATA>
            </STEP>
            <STEP step_id="12">
                <DATA>5</DATA>
                <DATA>8</DATA>
            </STEP>
            <STEP step_id="13">
                <DATA>7</DATA>
                <DATA>11</DATA>
            </STEP>
            <STEP step_id="14">
                <DATA>1</DATA>
                <DATA>5</DATA>
            </STEP>
            <STEP step_id="15">
                <DATA>2</DATA>
                <DATA>7</DATA>
            </STEP>
            <STEP step_id="16">
                <DATA>3</DATA>
                <DATA>7</DATA>
            </STEP>
            <STEP step_id="17">
                <DATA>1</DATA>
                <DATA>6</DATA>
            </STEP>
            <STEP step_id="18">
                <DATA>8</DATA>
                <DATA>13</DATA>
            </STEP>
            <STEP step_id="19">
                <DATA>6</DATA>
                <DATA>9</DATA>
            </STEP>
            <STEP step_id="20">
                <DATA>10</DATA>
                <DATA>14</DATA>
            </STEP>
            <STEP step_id="21">
                <DATA>5</DATA>
                <DATA>8</DATA>
            </STEP>
            <STEP step_id="22">
                <DATA>11</DATA>
                <DATA>15</DATA>
            </STEP>
            <STEP step_id="23">
                <DATA>12</DATA>
                <DATA>21</DATA>
                <DATA>21</DATA>
                <DATA>28</DATA>
            </STEP>
            <STEP step_id="24">
                <DATA>14</DATA>
                <DATA>18</DATA>
            </STEP>
            <STEP step_id="25">
                <DATA>9</DATA>
                <DATA>16</DATA>
            </STEP>
            <STEP step_id="26">
                <DATA>6</DATA>
                <DATA>10</DATA>
            </STEP>
            <STEP step_id="27">
                <DATA>28</DATA>
                <DATA>17</DATA>
            </STEP>
            <STEP step_id="28">
                <DATA>9</DATA>
                <DATA>18</DATA>
            </STEP>
            <STEP step_id="29">
                <DATA>15</DATA>
                <DATA>22</DATA>
            </STEP>
            <STEP step_id="30">
                <DATA>5</DATA>
                <DATA>14</DATA>
            </STEP>
            <STEP step_id="31">
                <DATA>16</DATA>
                <DATA>20</DATA>
            </STEP>
            <STEP step_id="32">
                <DATA>18</DATA>
                <DATA>22</DATA>
            </STEP>
            <STEP step_id="33">
                <DATA>20</DATA>
                <DATA>24</DATA>
            </STEP>
            <STEP step_id="34">
                <DATA>22</DATA>
                <DATA>25</DATA>
            </STEP>
            <STEP step_id="35">
                <DATA>24</DATA>
                <DATA>29</DATA>
            </STEP>
            <STEP step_id="36">
                <DATA>25</DATA>
                <DATA>29</DATA>
            </STEP>
            <STEP step_id="37">
                <DATA>10</DATA>
                <DATA>15</DATA>
            </STEP>
            <STEP step_id="38">
                <DATA>12</DATA>
                <DATA>21</DATA>
            </STEP>
            <STEP step_id="39">
                <DATA>7</DATA>
                <DATA>14</DATA>
                <DATA>14</DATA>
                <DATA>21</DATA>
            </STEP>
            <STEP step_id="40">
                <DATA>4</DATA>
                <DATA>8</DATA>
            </STEP>
            <STEP step_id="41">
                <DATA>11</DATA>
                <DATA>15</DATA>
            </STEP>
            <STEP step_id="42">
                <DATA>0</DATA>
                <DATA>4</DATA>
            </STEP>
            <STEP step_id="43">
                <DATA>15</DATA>
                <DATA>19</DATA>
            </STEP>
            <STEP step_id="44">
                <DATA>8</DATA>
                <DATA>13</DATA>
            </STEP>
            <STEP step_id="45">
                <DATA>29</DATA>
                <DATA>15</DATA>
            </STEP>
            <STEP step_id="46">
                <DATA>29</DATA>
                <DATA>15</DATA>
            </STEP>
            <STEP step_id="47">
                <DATA>15</DATA>
                <DATA>22</DATA>
            </STEP>
            <STEP step_id="48">
                <DATA>15</DATA>
                <DATA>6</DATA>
                <DATA>6</DATA>
                <DATA>13</DATA>
            </STEP>
            <STEP step_id="49">
                <DATA>19</DATA>
                <DATA>23</DATA>
            </STEP>
            <STEP step_id="50">
                <DATA>13</DATA>
                <DATA>20</DATA>
            </STEP>
            <STEP step_id="51">
                <DATA>23</DATA>
                <DATA>26</DATA>
            </STEP>
            <STEP step_id="52">
                <DATA>4</DATA>
                <DATA>8</DATA>
            </STEP>
            <STEP step_id="53">
                <DATA>26</DATA>
                <DATA>31</DATA>
            </STEP>
            <STEP step_id="54">
                <DATA>8</DATA>
                <DATA>13</DATA>
            </STEP>
            <STEP step_id="55">
                <DATA>8</DATA>
                <DATA>13</DATA>
            </STEP>
            <STEP step_id="56">
                <DATA>13</DATA>
                <DATA>17</DATA>
            </STEP>
            <STEP step_id="57">
                <DATA>13</DATA>
                <DATA>17</DATA>
            </STEP>
            <STEP step_id="58">
                <DATA>17</DATA>
                <DATA>22</DATA>
            </STEP>
            <STEP step_id="59">
                <DATA>4</DATA>
                <DATA>8</DATA>
            </STEP>
            <STEP step_id="60">
                <DATA>22</DATA>
                <DATA>26</DATA>
            </STEP>
            <STEP step_id="61">
                <DATA>0</DATA>
                <DATA>9</DATA>
            </STEP>
            <STEP step_id="62">
                <DATA>20</DATA>
                <DATA>16</DATA>
            </STEP>
            <STEP step_id="63">
                <DATA>17</DATA>
                <DATA>21</DATA>
            </STEP>
            <STEP step_id="64">
                <DATA>16</DATA>
                <DATA>20</DATA>
            </STEP>
            <STEP step_id="65">
                <DATA>21</DATA>
                <DATA>24</DATA>
            </STEP>
            <STEP step_id="66">
                <DATA>20</DATA>
                <DATA>2</DATA>
            </STEP>
            <STEP step_id="67">
                <DATA>24</DATA>
                <DATA>28</DATA>
            </STEP>
            <STEP step_id="68">
                <DATA>2</DATA>
                <DATA>9</DATA>
            </STEP>
            <STEP step_id="69">
                <DATA>31</DATA>
                <DATA>17</DATA>
            </STEP>
        </GAMESTEPS>
    </GAME>
    <GAME>
        <GAME_ID>4</GAME_ID>
        <PLAYER_1>Vitek</PLAYER_1>
        <PLAYER_2>Max</PLAYER_2>
        <DATE>1208694921</DATE>
        <ON_STEP>Max</ON_STEP>
        <FINISHED>0</FINISHED>
        <GAMESTEPS last_step_id="51">
            <STEP step_id="0">
                <DATA>11</DATA>
                <DATA>15</DATA>
            </STEP>
            <STEP step_id="1">
                <DATA>9</DATA>
                <DATA>13</DATA>
            </STEP>
            <STEP step_id="2">
                <DATA>15</DATA>
                <DATA>22</DATA>
            </STEP>
            <STEP step_id="3">
                <DATA>6</DATA>
                <DATA>13</DATA>
            </STEP>
            <STEP step_id="4">
                <DATA>8</DATA>
                <DATA>12</DATA>
            </STEP>
            <STEP step_id="5">
                <DATA>11</DATA>
                <DATA>15</DATA>
            </STEP>
            <STEP step_id="6">
                <DATA>7</DATA>
                <DATA>11</DATA>
            </STEP>
            <STEP step_id="7">
                <DATA>8</DATA>
                <DATA>12</DATA>
            </STEP>
            <STEP step_id="8">
                <DATA>10</DATA>
                <DATA>15</DATA>
            </STEP>
            <STEP step_id="9">
                <DATA>12</DATA>
                <DATA>21</DATA>
            </STEP>
            <STEP step_id="10">
                <DATA>6</DATA>
                <DATA>15</DATA>
                <DATA>15</DATA>
                <DATA>22</DATA>
            </STEP>
            <STEP step_id="11">
                <DATA>5</DATA>
                <DATA>14</DATA>
            </STEP>
            <STEP step_id="12">
                <DATA>9</DATA>
                <DATA>14</DATA>
            </STEP>
            <STEP step_id="13">
                <DATA>14</DATA>
                <DATA>21</DATA>
            </STEP>
            <STEP step_id="14">
                <DATA>3</DATA>
                <DATA>7</DATA>
            </STEP>
            <STEP step_id="15">
                <DATA>21</DATA>
                <DATA>28</DATA>
            </STEP>
            <STEP step_id="16">
                <DATA>5</DATA>
                <DATA>9</DATA>
            </STEP>
            <STEP step_id="17">
                <DATA>10</DATA>
                <DATA>14</DATA>
            </STEP>
            <STEP step_id="18">
                <DATA>12</DATA>
                <DATA>21</DATA>
            </STEP>
            <STEP step_id="19">
                <DATA>14</DATA>
                <DATA>17</DATA>
            </STEP>
            <STEP step_id="20">
                <DATA>9</DATA>
                <DATA>18</DATA>
            </STEP>
            <STEP step_id="21">
                <DATA>7</DATA>
                <DATA>14</DATA>
            </STEP>
            <STEP step_id="22">
                <DATA>18</DATA>
                <DATA>22</DATA>
            </STEP>
            <STEP step_id="23">
                <DATA>14</DATA>
                <DATA>18</DATA>
            </STEP>
            <STEP step_id="24">
                <DATA>1</DATA>
                <DATA>6</DATA>
            </STEP>
            <STEP step_id="25">
                <DATA>18</DATA>
                <DATA>23</DATA>
            </STEP>
            <STEP step_id="26">
                <DATA>4</DATA>
                <DATA>13</DATA>
            </STEP>
            <STEP step_id="27">
                <DATA>0</DATA>
                <DATA>5</DATA>
            </STEP>
            <STEP step_id="28">
                <DATA>22</DATA>
                <DATA>31</DATA>
            </STEP>
            <STEP step_id="29">
                <DATA>1</DATA>
                <DATA>5</DATA>
            </STEP>
            <STEP step_id="30">
                <DATA>31</DATA>
                <DATA>22</DATA>
            </STEP>
            <STEP step_id="31">
                <DATA>2</DATA>
                <DATA>6</DATA>
            </STEP>
            <STEP step_id="32">
                <DATA>22</DATA>
                <DATA>29</DATA>
            </STEP>
            <STEP step_id="33">
                <DATA>3</DATA>
                <DATA>7</DATA>
            </STEP>
            <STEP step_id="34">
                <DATA>29</DATA>
                <DATA>20</DATA>
            </STEP>
            <STEP step_id="35">
                <DATA>4</DATA>
                <DATA>8</DATA>
            </STEP>
            <STEP step_id="36">
                <DATA>13</DATA>
                <DATA>17</DATA>
            </STEP>
            <STEP step_id="37">
                <DATA>28</DATA>
                <DATA>10</DATA>
            </STEP>
            <STEP step_id="38">
                <DATA>6</DATA>
                <DATA>9</DATA>
            </STEP>
            <STEP step_id="39">
                <DATA>8</DATA>
                <DATA>13</DATA>
            </STEP>
            <STEP step_id="40">
                <DATA>9</DATA>
                <DATA>14</DATA>
            </STEP>
            <STEP step_id="41">
                <DATA>10</DATA>
                <DATA>21</DATA>
            </STEP>
            <STEP step_id="42">
                <DATA>11</DATA>
                <DATA>15</DATA>
            </STEP>
            <STEP step_id="43">
                <DATA>21</DATA>
                <DATA>12</DATA>
            </STEP>
            <STEP step_id="44">
                <DATA>2</DATA>
                <DATA>7</DATA>
            </STEP>
            <STEP step_id="45">
                <DATA>13</DATA>
                <DATA>16</DATA>
            </STEP>
            <STEP step_id="46">
                <DATA>7</DATA>
                <DATA>10</DATA>
            </STEP>
            <STEP step_id="47">
                <DATA>16</DATA>
                <DATA>25</DATA>
            </STEP>
            <STEP step_id="48">
                <DATA>20</DATA>
                <DATA>2</DATA>
            </STEP>
            <STEP step_id="49">
                <DATA>12</DATA>
                <DATA>25</DATA>
            </STEP>
            <STEP step_id="50">
                <DATA>2</DATA>
                <DATA>9</DATA>
            </STEP>
        </GAMESTEPS>
    </GAME>
    <GAME>
        <GAME_ID>16</GAME_ID>
        <PLAYER_1>Jarda</PLAYER_1>
        <PLAYER_2>Max</PLAYER_2>
        <DATE>1208695374</DATE>
        <ON_STEP>Jarda</ON_STEP>
        <FINISHED>0</FINISHED>
        <GAMESTEPS last_step_id="44">
            <STEP step_id="0">
                <DATA>11</DATA>
                <DATA>15</DATA>
            </STEP>
            <STEP step_id="1">
                <DATA>9</DATA>
                <DATA>13</DATA>
            </STEP>
            <STEP step_id="2">
                <DATA>15</DATA>
                <DATA>22</DATA>
            </STEP>
            <STEP step_id="3">
                <DATA>6</DATA>
                <DATA>13</DATA>
            </STEP>
            <STEP step_id="4">
                <DATA>9</DATA>
                <DATA>14</DATA>
            </STEP>
            <STEP step_id="5">
                <DATA>13</DATA>
                <DATA>22</DATA>
            </STEP>
            <STEP step_id="6">
                <DATA>5</DATA>
                <DATA>14</DATA>
            </STEP>
            <STEP step_id="7">
                <DATA>8</DATA>
                <DATA>13</DATA>
            </STEP>
            <STEP step_id="8">
                <DATA>14</DATA>
                <DATA>23</DATA>
            </STEP>
            <STEP step_id="9">
                <DATA>4</DATA>
                <DATA>13</DATA>
            </STEP>
            <STEP step_id="10">
                <DATA>10</DATA>
                <DATA>15</DATA>
            </STEP>
            <STEP step_id="11">
                <DATA>13</DATA>
                <DATA>20</DATA>
            </STEP>
            <STEP step_id="12">
                <DATA>7</DATA>
                <DATA>10</DATA>
            </STEP>
            <STEP step_id="13">
                <DATA>20</DATA>
                <DATA>24</DATA>
            </STEP>
            <STEP step_id="14">
                <DATA>2</DATA>
                <DATA>11</DATA>
            </STEP>
            <STEP step_id="15">
                <DATA>10</DATA>
                <DATA>14</DATA>
            </STEP>
            <STEP step_id="16">
                <DATA>10</DATA>
                <DATA>14</DATA>
            </STEP>
            <STEP step_id="17">
                <DATA>14</DATA>
                <DATA>21</DATA>
            </STEP>
            <STEP step_id="18">
                <DATA>6</DATA>
                <DATA>15</DATA>
            </STEP>
            <STEP step_id="19">
                <DATA>5</DATA>
                <DATA>9</DATA>
            </STEP>
            <STEP step_id="20">
                <DATA>15</DATA>
                <DATA>18</DATA>
            </STEP>
            <STEP step_id="21">
                <DATA>9</DATA>
                <DATA>16</DATA>
            </STEP>
            <STEP step_id="22">
                <DATA>11</DATA>
                <DATA>18</DATA>
            </STEP>
            <STEP step_id="23">
                <DATA>1</DATA>
                <DATA>6</DATA>
            </STEP>
            <STEP step_id="24">
                <DATA>18</DATA>
                <DATA>22</DATA>
            </STEP>
            <STEP step_id="25">
                <DATA>6</DATA>
                <DATA>13</DATA>
            </STEP>
            <STEP step_id="26">
                <DATA>3</DATA>
                <DATA>7</DATA>
            </STEP>
            <STEP step_id="27">
                <DATA>13</DATA>
                <DATA>17</DATA>
            </STEP>
            <STEP step_id="28">
                <DATA>7</DATA>
                <DATA>10</DATA>
            </STEP>
            <STEP step_id="29">
                <DATA>17</DATA>
                <DATA>24</DATA>
            </STEP>
            <STEP step_id="30">
                <DATA>1</DATA>
                <DATA>6</DATA>
            </STEP>
            <STEP step_id="31">
                <DATA>24</DATA>
                <DATA>29</DATA>
            </STEP>
            <STEP step_id="32">
                <DATA>6</DATA>
                <DATA>9</DATA>
            </STEP>
            <STEP step_id="33">
                <DATA>29</DATA>
                <DATA>18</DATA>
            </STEP>
            <STEP step_id="34">
                <DATA>8</DATA>
                <DATA>17</DATA>
            </STEP>
            <STEP step_id="35">
                <DATA>7</DATA>
                <DATA>10</DATA>
            </STEP>
            <STEP step_id="36">
                <DATA>17</DATA>
                <DATA>24</DATA>
            </STEP>
            <STEP step_id="37">
                <DATA>3</DATA>
                <DATA>10</DATA>
            </STEP>
            <STEP step_id="38">
                <DATA>4</DATA>
                <DATA>8</DATA>
            </STEP>
            <STEP step_id="39">
                <DATA>10</DATA>
                <DATA>14</DATA>
            </STEP>
            <STEP step_id="40">
                <DATA>0</DATA>
                <DATA>5</DATA>
            </STEP>
            <STEP step_id="41">
                <DATA>11</DATA>
                <DATA>15</DATA>
            </STEP>
            <STEP step_id="42">
                <DATA>8</DATA>
                <DATA>13</DATA>
            </STEP>
            <STEP step_id="43">
                <DATA>14</DATA>
                <DATA>23</DATA>
                <DATA>23</DATA>
                <DATA>30</DATA>
            </STEP>
        </GAMESTEPS>
    </GAME>
</GAMES>
